quickslides/__init__.py
quickslides/cli.py
quickslides/converter.py
typslides/.git
typslides/LICENSE
typslides/README.md
typslides/lib.typ
typslides/thumbnail.png
typslides/typslides.typ
typslides/typst.toml
typslides/utils.typ
typslides/template/bibliography.bib
typslides/template/main.typ
quickslides-0.1.7.dist-info/METADATA
quickslides-0.1.7.dist-info/WHEEL
quickslides-0.1.7.dist-info/entry_points.txt
quickslides-0.1.7.dist-info/RECORD
