Metadata-Version: 2.4
Name: quickslides
Version: 0.1.7
Summary: Convert Markdown to PDF slides using Typst and typslides
License: MIT
Requires-Python: >=3.12
Requires-Dist: click
Requires-Dist: mistune~=3.1.3
Requires-Dist: rich
